ukmdb_worker/__init__.py
ukmdb_worker/base.py
ukmdb_worker/queues.py
ukmdb_worker/worker.py
ukmdb_worker-0.0.3.dist-info/DESCRIPTION.rst
ukmdb_worker-0.0.3.dist-info/METADATA
ukmdb_worker-0.0.3.dist-info/RECORD
ukmdb_worker-0.0.3.dist-info/WHEEL
ukmdb_worker-0.0.3.dist-info/entry_points.txt
ukmdb_worker-0.0.3.dist-info/metadata.json
ukmdb_worker-0.0.3.dist-info/top_level.txt
