Metadata-Version: 2.0
Name: ukmdb-worker
Version: 0.0.3
Summary: UKMDB Worker processes.
Home-page: https://github.com/mleist/ukmdb_worker
Author: Markus Leist
Author-email: markus@lei.st
License: GPLv3
Keywords: ukmdb worker
Platform: UNKNOWN
Classifier: Development Status :: 3 - Alpha
Classifier: Intended Audience :: System Administrators
Classifier: Intended Audience :: Information Technology
Classifier: License :: OSI Approved :: GNU General Public License v3 or later (GPLv3+)
Classifier: Natural Language :: English
Classifier: Programming Language :: Python
Classifier: Programming Language :: Python :: 2
Classifier: Programming Language :: Python :: 2.7
Classifier: Programming Language :: Python :: 3
Classifier: Programming Language :: Python :: 3.4
Classifier: Programming Language :: Python :: 3.5
Classifier: Topic :: System :: Monitoring
Classifier: Topic :: System :: Logging
Classifier: Topic :: Internet :: Log Analysis
Classifier: Topic :: Software Development :: Libraries :: Python Modules
Requires-Dist: python-decouple
Requires-Dist: docopt
Requires-Dist: schema
Requires-Dist: celery (>=3.1)
Requires-Dist: ukmdb-settings
